warp_fastapi/__init__.py
warp_fastapi/app_object.py
warp_fastapi/app_project.py
warp_fastapi/attributes.py
warp_fastapi/base.py
warp_fastapi/code/__init__.py
warp_fastapi/code/alembic/alembic.py
warp_fastapi/code/code_objects/__init__.py
warp_fastapi/code/code_objects/base.py
warp_fastapi/code/code_objects/database.py
warp_fastapi/code/code_objects/dependacies.py
warp_fastapi/code/code_objects/main.py
warp_fastapi/code/code_objects/model.py
warp_fastapi/code/code_objects/repository.py
warp_fastapi/code/code_objects/routes.py
warp_fastapi/code/code_objects/schema.py
warp_fastapi/code/code_objects/security.py
warp_fastapi/code/code_objects/service.py
warp_fastapi/code/code_objects/settings.py
warp_fastapi/code/code_objects/tests.py
warp_fastapi/code/devops/docker.py
warp_fastapi/code/devops/dotenv.py
warp_fastapi/code/devops/git.py
warp_fastapi/code/devops/local.py
warp_fastapi/code/User/authentication.py
warp_fastapi/code/utils.py
warp_fastapi/config.py
warp_fastapi/create_project.py
warp_fastapi/data_types.py
warp_fastapi/exceptions.py
warp_fastapi/py.typed
warp_fastapi/relationships.py
warp_fastapi-0.1.1a1.dist-info/LICENSE
warp_fastapi-0.1.1a1.dist-info/METADATA
warp_fastapi-0.1.1a1.dist-info/WHEEL
warp_fastapi-0.1.1a1.dist-info/RECORD
