Metadata-Version: 2.1
Name: warp-fastapi
Version: 0.1.1a1
Summary: Create fastapi in a warp speed
Home-page: https://github.com/frenki123/warp_fastapi
License: MIT
Keywords: fastapi,code-generation,SQLAlchemy
Author: frenki123
Author-email: marko.frankola@gmail.com
Requires-Python: >=3.11,<4.0
Classifier: Framework :: FastAPI
Classifier: License :: OSI Approved :: MIT License
Classifier: Programming Language :: Python :: 3
Classifier: Programming Language :: Python :: 3.11
Classifier: Topic :: Software Development :: Code Generators
Requires-Dist: black (>=23.7.0,<24.0.0)
Requires-Dist: ordered-set (>=4.0.0,<5.0.0)
Requires-Dist: pydantic[email] (>=2.4.2,<3.0.0)
Requires-Dist: ruff (>=0.0.282,<0.0.283)
Project-URL: Documentation, https://frenki123.github.io/warp_fastapi
Project-URL: Repository, https://github.com/frenki123/warp_fastapi
